__init__.py
lumino/__init__.py
lumino/contracts_client/__init__.py
lumino/contracts_client/cli_utils.py
lumino/contracts_client/client.py
lumino/contracts_client/compute_power.py
lumino/contracts_client/config.py
lumino/contracts_client/constants.py
lumino/contracts_client/error_handler.py
lumino/contracts_client/event_handler.py
lumino/contracts_client/node_client.py
lumino/contracts_client/user_client.py
lumino/contracts_client/utils.py
lumino_contracts_client-0.3.1.dist-info/METADATA
lumino_contracts_client-0.3.1.dist-info/WHEEL
lumino_contracts_client-0.3.1.dist-info/entry_points.txt
lumino_contracts_client-0.3.1.dist-info/top_level.txt
lumino_contracts_client-0.3.1.dist-info/RECORD
