Metadata-Version: 2.2
Name: lumino-contracts-client
Version: 0.3.1
Summary: Client for interacting with the Lumino Labs protocol
Home-page: https://github.com/luminolabs/contracts-client
Author: Lumino Labs AI
Author-email: engg@luminolabs.ai
License: Apache License 2.0
Requires-Python: >=3.10
Requires-Dist: web3
Requires-Dist: eth-account
Requires-Dist: eth-typing
Requires-Dist: python-dotenv
Requires-Dist: eth_abi
Requires-Dist: click
Requires-Dist: pytest
Requires-Dist: setuptools
Requires-Dist: pynvml
Requires-Dist: psutil
Dynamic: author
Dynamic: author-email
Dynamic: description
Dynamic: description-content-type
Dynamic: home-page
Dynamic: license
Dynamic: requires-dist
Dynamic: requires-python
Dynamic: summary
